{"metadata": {"radius": 4.400000000000001, "n_clusters": 1, "n_clustered": 36, "n_singular": 5, "n_rnas": 3, "n_total": 45, "singular_chains": ["eL19", "eL22", "eL31", "eL38", "eL41"], "rnas": ["A", "B", "C"], "allchains": ["A", "B", "C", "uL2", "uL3", "uL4", "uL5", "uL6", "I", "eL30", "uL13", "eL13", "uL14", "eL14", "uL15", "eL15", "uL16", "uL18", "eL18", "eL19", "eL20", "eL21", "uL22", "eL22", "uL23", "uL24", "eL24", "eL27", "eL28", "uL29", "eL29", "uL30", "eL30", "eL31", "eL32", "eL33", "eL34", "eL36", "eL37", "eL38", "eL39", "eL40", "eL41", "eL43", "eL42"]}, "clusters": [["uL4", "uL24", "uL14", "uL6", "eL33", "eL14", "eL20", "eL32", "eL24", "eL34", "I", "uL18", "uL3", "uL2", "eL36", "eL21", "eL29", "eL40", "eL27", "uL5", "eL13", "uL13", "uL23", "uL22", "eL42", "uL29", "eL30", "eL28", "eL37", "eL39", "uL16", "uL15", "uL30", "eL18", "eL15", "eL43"]], "nbrtree": {"eL13": ["uL15", "uL4", "eL18", "eL15", "uL29", "eL36"], "uL15": ["eL13", "eL32", "eL42", "eL18", "eL36"], "uL6": ["uL13", "eL20", "eL40", "eL14"], "uL13": ["uL6", "uL3", "eL20", "eL14", "I", "eL33"], "eL27": ["eL34", "eL30"], "eL34": ["eL27", "eL30", "eL39", "eL43", "uL2"], "uL4": ["eL15", "eL37", "eL20", "uL24", "I", "eL18", "eL28", "eL13", "eL21", "uL30"], "eL15": ["uL4", "uL29", "eL42", "uL2", "eL30", "eL36", "eL13"], "eL37": ["uL4", "eL39", "uL29"], "uL3": ["uL13", "uL14", "eL24"], "eL24": ["uL14", "uL3"], "uL14": ["eL24", "uL3"], "eL20": ["uL4", "uL13", "uL16", "uL30", "eL21", "eL33", "uL6", "I", "eL14"], "uL24": ["uL4"], "eL32": ["uL15", "eL28", "eL33"], "eL39": ["eL37", "eL34", "uL23"], "eL42": ["uL15", "eL15"], "eL30": ["eL43", "eL34", "eL36", "uL2", "eL15", "eL27"], "eL43": ["eL30", "eL34", "uL2"], "uL29": ["uL23", "eL15", "eL37", "eL13"], "uL23": ["uL29", "eL39"], "eL36": ["eL30", "uL15", "eL15", "eL13"], "uL16": ["uL18", "eL20"], "uL18": ["uL16", "uL5", "eL29", "eL21"], "I": ["uL4", "eL33", "uL13", "eL14", "eL20", "uL22"], "eL28": ["eL32", "uL4", "eL18"], "eL33": ["I", "eL32", "eL20", "uL13"], "eL18": ["uL4", "uL30", "eL13", "uL15", "eL28"], "uL5": ["uL18"], "eL14": ["uL13", "I", "uL6", "eL20"], "uL2": ["eL30", "eL15", "eL34", "eL43"], "uL30": ["eL18", "uL4", "eL20", "eL21"], "eL21": ["uL4", "eL20", "uL18", "uL30", "eL29"], "eL29": ["uL18", "eL21"], "eL40": ["uL6"], "uL22": ["I"]}}