{"metadata": {"radius": 2.6000000000000014, "n_clusters": 6, "n_clustered": 12, "n_singular": 17, "n_rnas": 2, "n_total": 31, "singular_chains": ["bL33", "bL34", "bL36", "uL2", "uL3", "uL4", "uL6", "uL13", "uL14", "bL17", "O", "bL19", "uL23", "uL24", "bL27", "uL29", "uL30"], "rnas": ["A", "B"], "allchains": ["bL32", "bL33", "bL34", "bL35", "bL36", "bL31", "A", "B", "uL2", "uL3", "uL4", "uL5", "uL6", "bL9", "uL13", "uL14", "uL15", "uL16", "bL17", "O", "bL19", "bL20", "bL21", "uL22", "uL23", "uL24", "bL25", "bL27", "bL28", "uL29", "uL30"]}, "clusters": [["bL20", "bL21"], ["uL5", "bL31"], ["bL28", "bL9"], ["bL35", "uL15"], ["bL25", "uL16"], ["uL22", "bL32"]], "nbrtree": {"bL20": ["bL21"], "bL21": ["bL20"], "bL31": ["uL5"], "uL5": ["bL31"], "bL9": ["bL28"], "bL28": ["bL9"], "bL35": ["uL15"], "uL15": ["bL35"], "uL16": ["bL25"], "bL25": ["uL16"], "bL32": ["uL22"], "uL22": ["bL32"]}}